djangoflutterwave/__init__.py
djangoflutterwave/admin.py
djangoflutterwave/apps.py
djangoflutterwave/migrations/0001_initial.py
djangoflutterwave/migrations/0002_auto_20201222_0800.py
djangoflutterwave/migrations/__init__.py
djangoflutterwave/models.py
djangoflutterwave/serializers.py
djangoflutterwave/settings.py
djangoflutterwave/static/djangoflutterwave/js/payment.js
djangoflutterwave/templates/djangoflutterwave/pay_button.html
djangoflutterwave/templates/djangoflutterwave/transaction.html
djangoflutterwave/templatetags/__init__.py
djangoflutterwave/templatetags/djangoflutterwave_tags.py
djangoflutterwave/tests/__init__.py
djangoflutterwave/tests/factories.py
djangoflutterwave/tests/test_serializers.py
djangoflutterwave/tests/test_template_tags.py
djangoflutterwave/tests/test_views.py
djangoflutterwave/urls.py
djangoflutterwave/views.py
djangoflutterwave-0.2.3.dist-info/LICENSE
djangoflutterwave-0.2.3.dist-info/WHEEL
djangoflutterwave-0.2.3.dist-info/METADATA
djangoflutterwave-0.2.3.dist-info/RECORD
